<ids>
        <id>9000417559</id>
        <id>9000332563</id>
        <id>9000332890</id>
        <id>9000417970</id>
        <id>9000418019</id>
        <id>9000418532</id>
        <id>9000335059</id>
        <id>9000335194</id>
        <id>9000417817</id>
        <id>9000335353</id>
        <id>9000335423</id>
        <id>9000335209</id>
        <id>9000346246</id>
        <id>9000425321</id>
        <id>9000341279</id>
        <id>9000335371</id>
        <id>9000332708</id>
        <id>9000335439</id>
        <id>9000417806</id>
        <id>9000369124</id>
        <id>9000369831</id>
        <id>9000417854</id>
        <id>9000336740</id>
        <id>9000343813</id>
        <id>9000345466</id>
        <id>9000346567</id>
        <id>9000335445</id>
        <id>9000335445</id>
        <id>9000347138</id>
        <id>9000413190</id>
        <id>9000341240</id>
        <id>9000341438</id>
        <id>9000341294</id>
        <id>9000341440</id>
        <id>9000341447</id>
        <id>9000351945</id>
        <id>9000344089</id>
        <id>9000347123</id>
        <id>9000346247</id>
        <id>9000439103</id>
</ids>
